{
  "id": "prt_99b3ff771001vWp7AIDfS2VUUo",
  "messageID": "msg_99b3fd2850018Rt3ZnloXPlc1D",
  "sessionID": "ses_6852784ecffeuHwynj83p2lr14",
  "type": "text",
  "text": "Анализируя лог, я вижу:\n\n**🔍 КОРЕНЬ ПРОБЛЕМЫ:**\n```json\n\"derival\": {\n  \"terminalID\": null,  // ❌ ВОТ ПРОБЛЕМА!\n},\n\"arrival\": {\n  \"terminalID\": null,  // ❌ И ЗДЕСЬ!\n}\n```\n\n**📋 Ошибки от API:**\n- \"Это поле не может быть null\" \n- \"Требуется указать терминал\"\n\n**🎯 РЕШЕНИЕ:** API получает `terminalID: null` и возвращает ошибку 400, из-за чего `data.data` становится `undefined`, а затем код пытается обратиться к `undefined.derival`.\n\nДавайте посмотрим на логику получения терминалов:",
  "time": {
    "start": 1759246288724,
    "end": 1759246288724
  }
}