{
  "id": "prt_9e32217a4001n4xciJvEJ4DydY",
  "messageID": "msg_9e322106c001UlpLFLoFVqyHCD",
  "sessionID": "ses_6852784ecffeuHwynj83p2lr14",
  "type": "tool",
  "tool": "grep",
  "callID": "call_25688489",
  "state": {
    "status": "completed",
    "input": {
      "pattern": "tariff_details",
      "path": "app/page.tsx"
    },
    "output": "No files found",
    "metadata": {
      "matches": 0,
      "truncated": false
    },
    "title": "tariff_details",
    "time": {
      "start": 1760452286375,
      "end": 1760452286381
    }
  }
}