{
  "id": "prt_ab373798c001OcKtDBdxZSpi3w",
  "sessionID": "ses_6852784ecffeuHwynj83p2lr14",
  "messageID": "msg_ab373798a001GV7ObkgVH4ZPor",
  "type": "text",
  "text": "Проверь ошибку и исправь\n\nFailed to compile\n\nNext.js (14.2.31) is outdated (learn more)\n./app/page.tsx\nError: \n  x Unexpected token `div`. Expected jsx identifier\n      ,-[/home/user/project/app/page.tsx:4462:1]\n 4462 |   }\n 4463 | \n 4464 |   return (\n 4465 |     <div className=\"min-h-screen bg-gray-900 text-white p-4 relative\">\n      :      ^^^\n 4466 |       <div className=\"max-w-7xl mx-auto\">\n 4467 |         <div className=\"flex items-center justify-between mb-3\">\n 4468 |           <h1 className=\"text-xl font-bold text-blue-400\">\n      `----"
}