{
  "id": "prt_b22cf5e6a001cAW6B3k0j3fyV4",
  "sessionID": "ses_4dd34592affehJqMoLA2ZOxuZo",
  "messageID": "msg_b22cf4e99001A2Ce4tgwVuvNFE",
  "type": "tool",
  "callID": "toolu_01BZzK3ANjNsUsv83iu5mPFs",
  "tool": "bash",
  "state": {
    "status": "completed",
    "input": {
      "command": "cd /home/user/project && npm run build 2>&1 | tail -30",
      "description": "Build project to verify no errors",
      "timeout": 120000
    },
    "output": "\n> ideavo-nextjs@0.1.0 build\n> next build\n\n  ▲ Next.js 14.2.31\n  - Environments: .env.local, .env\n\n   Creating an optimized production build ...\n ✓ Compiled successfully\n   Linting and checking validity of types ...\nFailed to compile.\n\n./app/api/vozovoz-parser-stable/route.ts:484:35\nType error: Type 'NodeListOf<Element>' can only be iterated through when using the '--downlevelIteration' flag or with a '--target' of 'es2015' or higher.\n\n\u001b[0m \u001b[90m 482 |\u001b[39m           \u001b[36mtry\u001b[39m {\u001b[0m\n\u001b[0m \u001b[90m 483 |\u001b[39m             \u001b[36mconst\u001b[39m elements \u001b[33m=\u001b[39m document\u001b[33m.\u001b[39mquerySelectorAll(selector)\u001b[33m;\u001b[39m\u001b[0m\n\u001b[0m\u001b[31m\u001b[1m>\u001b[22m\u001b[39m\u001b[90m 484 |\u001b[39m             \u001b[36mfor\u001b[39m (\u001b[36mconst\u001b[39m element \u001b[36mof\u001b[39m elements) {\u001b[0m\n\u001b[0m \u001b[90m     |\u001b[39m                                   \u001b[31m\u001b[1m^\u001b[22m\u001b[39m\u001b[0m\n\u001b[0m \u001b[90m 485 |\u001b[39m               \u001b[36mconst\u001b[39m text \u001b[33m=\u001b[39m element\u001b[33m.\u001b[39mtextContent \u001b[33m||\u001b[39m \u001b[32m''\u001b[39m\u001b[33m;\u001b[39m\u001b[0m\n\u001b[0m \u001b[90m 486 |\u001b[39m               \u001b[36mconst\u001b[39m priceMatch \u001b[33m=\u001b[39m text\u001b[33m.\u001b[39mmatch(\u001b[35m/(\\d[\\s\\d]*\\d+)\\s*₽/\u001b[39m)\u001b[33m;\u001b[39m\u001b[0m\n\u001b[0m \u001b[90m 487 |\u001b[39m               \u001b[36mif\u001b[39m (priceMatch) {\u001b[0m\nNext.js build worker exited with code: 1 and signal: null\n",
    "title": "Build project to verify no errors",
    "metadata": {
      "output": "\n> ideavo-nextjs@0.1.0 build\n> next build\n\n  ▲ Next.js 14.2.31\n  - Environments: .env.local, .env\n\n   Creating an optimized production build ...\n ✓ Compiled successfully\n   Linting and checking validity of types ...\nFailed to compile.\n\n./app/api/vozovoz-parser-stable/route.ts:484:35\nType error: Type 'NodeListOf<Element>' can only be iterated through when using the '--downlevelIteration' flag or with a '--target' of 'es2015' or higher.\n\n\u001b[0m \u001b[90m 482 |\u001b[39m           \u001b[36mtry\u001b[39m {\u001b[0m\n\u001b[0m \u001b[90m 483 |\u001b[39m             \u001b[36mconst\u001b[39m elements \u001b[33m=\u001b[39m document\u001b[33m.\u001b[39mquerySelectorAll(selector)\u001b[33m;\u001b[39m\u001b[0m\n\u001b[0m\u001b[31m\u001b[1m>\u001b[22m\u001b[39m\u001b[90m 484 |\u001b[39m             \u001b[36mfor\u001b[39m (\u001b[36mconst\u001b[39m element \u001b[36mof\u001b[39m elements) {\u001b[0m\n\u001b[0m \u001b[90m     |\u001b[39m                                   \u001b[31m\u001b[1m^\u001b[22m\u001b[39m\u001b[0m\n\u001b[0m \u001b[90m 485 |\u001b[39m               \u001b[36mconst\u001b[39m text \u001b[33m=\u001b[39m element\u001b[33m.\u001b[39mtextContent \u001b[33m||\u001b[39m \u001b[32m''\u001b[39m\u001b[33m;\u001b[39m\u001b[0m\n\u001b[0m \u001b[90m 486 |\u001b[39m               \u001b[36mconst\u001b[39m priceMatch \u001b[33m=\u001b[39m text\u001b[33m.\u001b[39mmatch(\u001b[35m/(\\d[\\s\\d]*\\d+)\\s*₽/\u001b[39m)\u001b[33m;\u001b[39m\u001b[0m\n\u001b[0m \u001b[90m 487 |\u001b[39m               \u001b[36mif\u001b[39m (priceMatch) {\u001b[0m\nNext.js build worker exited with code: 1 and signal: null\n",
      "exit": 0,
      "description": "Build project to verify no errors"
    },
    "time": {
      "start": 1765815574371,
      "end": 1765815586471
    }
  }
}