{
  "id": "prt_9b8e3fb14001KSSsTb3e02nHb0",
  "messageID": "msg_9b8e348d5001yimlGUAUuSJzNQ",
  "sessionID": "ses_6852784ecffeuHwynj83p2lr14",
  "type": "tool",
  "tool": "edit",
  "callID": "toolu_018YNKzjCYfcTb2QSZjw4vu8",
  "state": {
    "status": "completed",
    "input": {
      "filePath": "/home/user/project/next.config.js",
      "oldString": "/** @type {import('next').NextConfig} */\nconst nextConfig = {\n  images: { unoptimized: true },\n  \n  // Отключаем кэширование для разработки\n  experimental: {\n    serverActions: {\n      allowedOrigins: ['localhost:3000']\n    },\n    // Более агрессивный hot reload\n    optimisticClientCache: false,\n  },\n  \n  // Отключаем кэш статических файлов\n  assetPrefix: process.env.NODE_ENV === 'development' ? '' : undefined,\n  \n  // Принудительная перезагрузка при изменениях\n  reactStrictMode: true,\n  \n  // Быстрая перезагрузка включена по умолчанию в Next.js 14\n  \n  // Отключаем кэш сборки в dev режиме\n  webpack: (config, { dev }) => {\n    if (dev) {\n      config.cache = false;\n    }\n    return config;\n  }\n};\n\nmodule.exports = nextConfig;",
      "newString": "/** @type {import('next').NextConfig} */\nconst nextConfig = {\n  images: { unoptimized: true },\n  \n  // Настройки для лучшего dev experience\n  experimental: {\n    // Отключаем клиентский кэш только в dev режиме\n    optimisticClientCache: process.env.NODE_ENV === 'development' ? false : true,\n  },\n  \n  // Принудительная перезагрузка при изменениях\n  reactStrictMode: true,\n  \n  // Настройки webpack для dev режима (более мягкие)\n  webpack: (config, { dev, isServer }) => {\n    if (dev) {\n      // Используем memory cache вместо полного отключения\n      config.cache = {\n        type: 'memory',\n        maxGenerations: 1,\n      };\n    }\n    \n    return config;\n  },\n  \n  // Добавляем заголовки для dev режима\n  async headers() {\n    if (process.env.NODE_ENV === 'development') {\n      return [\n        {\n          source: '/(.*)',\n          headers: [\n            {\n              key: 'Cache-Control',\n              value: 'no-cache, no-store, must-revalidate',\n            },\n            {\n              key: 'Pragma',\n              value: 'no-cache',\n            },\n            {\n              key: 'Expires',\n              value: '0',\n            },\n          ],\n        },\n      ];\n    }\n    return [];\n  },\n};\n\nmodule.exports = nextConfig;"
    },
    "output": "",
    "metadata": {
      "diagnostics": {},
      "diff": "Index: /home/user/project/next.config.js\n===================================================================\n--- /home/user/project/next.config.js\n+++ /home/user/project/next.config.js\n@@ -1,31 +1,54 @@\n /** @type {import('next').NextConfig} */\n const nextConfig = {\n   images: { unoptimized: true },\n   \n-  // Отключаем кэширование для разработки\n+  // Настройки для лучшего dev experience\n   experimental: {\n-    serverActions: {\n-      allowedOrigins: ['localhost:3000']\n-    },\n-    // Более агрессивный hot reload\n-    optimisticClientCache: false,\n+    // Отключаем клиентский кэш только в dev режиме\n+    optimisticClientCache: process.env.NODE_ENV === 'development' ? false : true,\n   },\n   \n-  // Отключаем кэш статических файлов\n-  assetPrefix: process.env.NODE_ENV === 'development' ? '' : undefined,\n-  \n   // Принудительная перезагрузка при изменениях\n   reactStrictMode: true,\n   \n-  // Быстрая перезагрузка включена по умолчанию в Next.js 14\n-  \n-  // Отключаем кэш сборки в dev режиме\n-  webpack: (config, { dev }) => {\n+  // Настройки webpack для dev режима (более мягкие)\n+  webpack: (config, { dev, isServer }) => {\n     if (dev) {\n-      config.cache = false;\n+      // Используем memory cache вместо полного отключения\n+      config.cache = {\n+        type: 'memory',\n+        maxGenerations: 1,\n+      };\n     }\n+    \n     return config;\n-  }\n+  },\n+  \n+  // Добавляем заголовки для dev режима\n+  async headers() {\n+    if (process.env.NODE_ENV === 'development') {\n+      return [\n+        {\n+          source: '/(.*)',\n+          headers: [\n+            {\n+              key: 'Cache-Control',\n+              value: 'no-cache, no-store, must-revalidate',\n+            },\n+            {\n+              key: 'Pragma',\n+              value: 'no-cache',\n+            },\n+            {\n+              key: 'Expires',\n+              value: '0',\n+            },\n+          ],\n+        },\n+      ];\n+    }\n+    return [];\n+  },\n };\n \n module.exports = nextConfig;\n"
    },
    "title": "next.config.js",
    "time": {
      "start": 1759743578893,
      "end": 1759743578902
    }
  }
}