{
  "id": "prt_98d0f4198001e2qB52iRfIJjiu",
  "messageID": "msg_98d0f073b001MS3rclNqNwCGpG",
  "sessionID": "ses_6852784ecffeuHwynj83p2lr14",
  "type": "tool",
  "tool": "read",
  "callID": "toolu_019DqvgQjS6kbBqvihh1KrUN",
  "state": {
    "status": "completed",
    "input": {
      "filePath": "/home/user/project/app/page.tsx",
      "offset": 1418,
      "limit": 20
    },
    "output": "<file>\n01419|       // Формируем массив грузов (без координат)\n01420|       const cargos = form.cargos.map(cargo => {\n01421|         const cargoData = {\n01422|           length: cargo.length / 100, // переводим см в метры\n01423|           width: cargo.width / 100,\n01424|           height: cargo.height / 100,\n01425|           volume: (cargo.length * cargo.width * cargo.height) / 1000000, // м3\n01426|           weight: cargo.weight,\n01427|           isHP: form.needPackaging, // защитная упаковка\n01428|           sealingPositionsCount: 0\n01429|         };\n01430|         \n01431|         console.log('📦 Груз для ПЭК:', cargoData);\n01432|         return cargoData;\n01433|       });\n01434| \n01435|       // Переменная для хранения финального запроса (нужна для возврата в результате)\n01436|       let finalRequestData: any = null;\n01437|       \n01438|       // Функция для попытки расчета с конкретной датой\n\n(File has more lines. Use 'offset' parameter to read beyond line 1438)\n</file>",
    "metadata": {
      "preview": "      // Формируем массив грузов (без координат)\n      const cargos = form.cargos.map(cargo => {\n        const cargoData = {\n          length: cargo.length / 100, // переводим см в метры\n          width: cargo.width / 100,\n          height: cargo.height / 100,\n          volume: (cargo.length * cargo.width * cargo.height) / 1000000, // м3\n          weight: cargo.weight,\n          isHP: form.needPackaging, // защитная упаковка\n          sealingPositionsCount: 0\n        };\n        \n        console.log('📦 Груз для ПЭК:', cargoData);\n        return cargoData;\n      });\n\n      // Переменная для хранения финального запроса (нужна для возврата в результате)\n      let finalRequestData: any = null;\n      \n      // Функция для попытки расчета с конкретной датой"
    },
    "title": "app/page.tsx",
    "time": {
      "start": 1759008212129,
      "end": 1759008212134
    }
  }
}