{
  "id": "prt_995239689001QIDQPbp0Wp2yo5",
  "messageID": "msg_995224e5d001Y8Mw3xK5yof1sx",
  "sessionID": "ses_6852784ecffeuHwynj83p2lr14",
  "type": "tool",
  "tool": "todowrite",
  "callID": "toolu_01YQsTpUFHmTmSLYNH6uqm1C",
  "state": {
    "status": "completed",
    "input": {
      "todos": [
        {
          "content": "Set default Y-axis rotation to 50 degrees",
          "status": "completed",
          "priority": "medium",
          "id": "1"
        },
        {
          "content": "Double the width of truck visualization window",
          "status": "completed",
          "priority": "high",
          "id": "2"
        },
        {
          "content": "Move cargo legend below truck visualization",
          "status": "completed",
          "priority": "medium",
          "id": "3"
        }
      ]
    },
    "output": "[\n  {\n    \"content\": \"Set default Y-axis rotation to 50 degrees\",\n    \"status\": \"completed\",\n    \"priority\": \"medium\",\n    \"id\": \"1\"\n  },\n  {\n    \"content\": \"Double the width of truck visualization window\",\n    \"status\": \"completed\",\n    \"priority\": \"high\",\n    \"id\": \"2\"\n  },\n  {\n    \"content\": \"Move cargo legend below truck visualization\",\n    \"status\": \"completed\",\n    \"priority\": \"medium\",\n    \"id\": \"3\"\n  }\n]",
    "metadata": {
      "todos": [
        {
          "content": "Set default Y-axis rotation to 50 degrees",
          "status": "completed",
          "priority": "medium",
          "id": "1"
        },
        {
          "content": "Double the width of truck visualization window",
          "status": "completed",
          "priority": "high",
          "id": "2"
        },
        {
          "content": "Move cargo legend below truck visualization",
          "status": "completed",
          "priority": "medium",
          "id": "3"
        }
      ]
    },
    "title": "0 todos",
    "time": {
      "start": 1759143763743,
      "end": 1759143763744
    }
  }
}