{
  "id": "prt_99b31d9d2001Dw1mauMoxp0I4F",
  "messageID": "msg_99b303c570014LTphYnlxdv0vr",
  "sessionID": "ses_6852784ecffeuHwynj83p2lr14",
  "type": "text",
  "text": "Я вижу потенциальную проблему в строке 2878! Там есть условие `if (calc.details.derival?.price)`, но затем внутри идет обращение `calc.details.derival.price` без опциональной цепочки. Если `calc.details.derival` равен `null`, то это может вызвать ошибку. Давайте исправим это:",
  "time": {
    "start": 1759245361652,
    "end": 1759245361652
  }
}