{
  "id": "prt_9b9a9c6120015Ychga3o8U3asL",
  "messageID": "msg_9b9a4df3c001MvmGtfFtdzuTje",
  "sessionID": "ses_6852784ecffeuHwynj83p2lr14",
  "type": "text",
  "text": "## Summary\n\nЯ успешно реализовал все запрошенные изменения:\n\n### 🔧 Исправления Dellin API для поиска терминалов\n\n**Проблема**: Запрос к API терминалов Dellin был неполным и не содержал необходимые поля.\n\n**Решение**: Обновил структуру запроса согласно спецификации API:\n\n```typescript\nconst requestBody = {\n  appkey: 'E6C50E91-8E93-440F-9CC6-DEF9F0D68F1B',\n  sessionID: sessionID,\n  search: normalizedCity,\n  direction: direction,\n  maxCargoDimensions: {\n    length: 3.0,\n    width: 3.0,\n    height: 3.0,\n    weight: 3.0,\n    maxVolume: 3.0,\n    totalVolume: 3.0,\n    totalWeight: 3.0\n  },\n  express: true,\n  freeStorageDays: \"2\"\n};\n```\n\n### ✅ Добавлен чекбокс \"Со склада Лавсит\"\n\n**Расположение**: В блоке \"Маршрут\" → \"Отправление\", после радиокнопок \"От терминала\" и \"От адреса\"\n\n**Функционал**:\n- При активации автоматически устанавливает режим \"От адреса\"\n- Автоматически заполняет адрес: `деревня Осеево, 202, городской округ Лосино-Петровский, Московская область`\n- Автоматически заполняет город: `Лосино-Петровский`\n- При активации блокирует ручное редактирование полей адреса\n- При деактивации очищает поля и разблокирует их\n\n### 🏢 Координаты склада Лавсит (резерв)\n\nВ случае если API не найдет адрес, можно использовать координаты: `55.885832, 38.157927`\n\n### 💾 Обновлена система сохранения\n\n- Добавлено поле `fromLavsiteWarehouse` в интерфейс формы\n- Обновлена система persistence с миграцией данных (версия 1.1)\n- Данные о выборе склада Лавсит сохраняются и восстанавливаются\n\n### 🎯 Что изменилось в UI\n\n1. **Новый чекбокс** под радиокнопками отправления\n2. **Автоматическое заполнение** адреса при выборе склада\n3. **Блокировка полей** когда активен режим склада Лавсит\n4. **Правильная логика** переключения между режимами\n\n### ✅ Протестировано\n\n- TypeScript компиляция без ошибок\n- Сборка проекта успешна\n- Сервер разработки запускается корректно\n- Система миграции данных обновлена\n\nТеперь пользователи могут легко выбрать отправку со склада Лавсит одним кликом, а система автоматически заполнит нужный адрес и заблокирует ручное редактирование для предотвращения ошибок.",
  "time": {
    "start": 1759756552864,
    "end": 1759756552864
  }
}