{
  "id": "prt_9b9c07055001JwMCYrjJkHr6xx",
  "messageID": "msg_9b9bd7fd70013nR5OyAR9LVDZ4",
  "sessionID": "ses_6852784ecffeuHwynj83p2lr14",
  "type": "tool",
  "tool": "bash",
  "callID": "toolu_019RmYMzeRq3Sexwf1628ArR",
  "state": {
    "status": "completed",
    "input": {
      "command": "cd /home/user/project && node test-dellin-places.js",
      "timeout": 30000,
      "description": "Test the new Dellin places API"
    },
    "output": "🧪 Тестирование API справочника мест Деловых Линий...\n\n📍 Тест 1: Поиск cityID для Москвы\n",
    "metadata": {
      "output": "🧪 Тестирование API справочника мест Деловых Линий...\n\n📍 Тест 1: Поиск cityID для Москвы\n",
      "exit": null,
      "description": "Test the new Dellin places API"
    },
    "title": "cd /home/user/project && node test-dellin-places.js",
    "time": {
      "start": 1759758021677,
      "end": 1759758051688
    }
  }
}