{
  "id": "prt_ab8c6cf99001xa0JrQW06gehuR",
  "sessionID": "ses_54b97e247ffenCZZa4jZiIWD0l",
  "messageID": "msg_ab8c6a767001GO4d3BME7k9yCR",
  "type": "tool",
  "callID": "call_ce97dfa26a9a4912b61d170c",
  "tool": "read",
  "state": {
    "status": "completed",
    "input": {
      "filePath": "/home/user/project/app/page.tsx",
      "limit": 30,
      "offset": 5310
    },
    "output": "<file>\n05311|                  <div className=\"space-y-2\">\n05312|                 <div className=\"flex justify-between items-center\">\n05313|                   <h2 className=\"text-lg font-bold text-blue-400\">Результаты расчета</h2>\n05314|                   <Button \n05315|                     onClick={exportToPDF} \n05316|                     variant=\"outline\" \n05317|                     size=\"sm\" \n05318|                     className=\"h-7 text-xs border-blue-500 text-blue-400 hover:bg-blue-900/20 print:hidden\"\n05319|                   >\n05320|                     Сохранить в PDF\n05321|                   </Button>\n05322|                 </div>\n05323|                 \n05324|                 {calculations\n05325|                   .filter(calc => !hiddenCompanies[calc.company])\n05326|                   .map((calc, index) => (\n05327|                    <Card key={index} className=\"bg-gray-800 border-gray-700 text-xs\">\n05328|                      <CardHeader className=\"pb-1\">\n05329|                       <div className=\"flex justify-between items-center\">\n05330|                          <CardTitle className=\"text-white flex items-center gap-2 text-xs\">\n05331|                            <Building2 className=\"h-3 w-3\" />\n05332|                           {calc.company}\n05333|                         </CardTitle>\n05334|                         {calc.error ? (\n05335|                           <Badge variant=\"destructive\" className=\"text-xs\">Ошибка</Badge>\n05336|                         ) : (\n05337|                           <Badge variant=\"default\" className=\"bg-green-600 text-xs\">\n05338|                             {calc.price.toLocaleString()} ₽\n05339|                           </Badge>\n05340|                         )}\n\n(File has more lines. Use 'offset' parameter to read beyond line 5340)\n</file>",
    "title": "app/page.tsx",
    "metadata": {
      "preview": "                 <div className=\"space-y-2\">\n                <div className=\"flex justify-between items-center\">\n                  <h2 className=\"text-lg font-bold text-blue-400\">Результаты расчета</h2>\n                  <Button \n                    onClick={exportToPDF} \n                    variant=\"outline\" \n                    size=\"sm\" \n                    className=\"h-7 text-xs border-blue-500 text-blue-400 hover:bg-blue-900/20 print:hidden\"\n                  >\n                    Сохранить в PDF\n                  </Button>\n                </div>\n                \n                {calculations\n                  .filter(calc => !hiddenCompanies[calc.company])\n                  .map((calc, index) => (\n                   <Card key={index} className=\"bg-gray-800 border-gray-700 text-xs\">\n                     <CardHeader className=\"pb-1\">\n                      <div className=\"flex justify-between items-center\">\n                         <CardTitle className=\"text-white flex items-center gap-2 text-xs\">"
    },
    "time": {
      "start": 1764036628381,
      "end": 1764036628392
    }
  }
}